LICENSE
README.md
setup.py
src/ds_dev_utils/__init__.py
src/ds_dev_utils/azure_utils/__init__.py
src/ds_dev_utils/azure_utils/blob.py
src/ds_dev_utils/azure_utils/validators/__init__.py
src/ds_dev_utils/azure_utils/validators/blob_config_validator.py
src/ds_dev_utils/exe/__init__.py
src/ds_dev_utils/exe/azure_blob/__init__.py
src/ds_dev_utils/unit_tests/__init__.py
src/ds_dev_utils/unit_tests/conftest.py
src/ds_dev_utils/unit_tests/test_blob.py
src/ds_dev_utils/unit_tests/mock/__init__.py
src/ds_dev_utils/unit_tests/mock/mock.py
src/ds_dev_utils/unit_tests/mock/mock_file_storage/__init__.py
src/pg_rd_cf_ai_pset_2_sandhan_b.egg-info/PKG-INFO
src/pg_rd_cf_ai_pset_2_sandhan_b.egg-info/SOURCES.txt
src/pg_rd_cf_ai_pset_2_sandhan_b.egg-info/dependency_links.txt
src/pg_rd_cf_ai_pset_2_sandhan_b.egg-info/entry_points.txt
src/pg_rd_cf_ai_pset_2_sandhan_b.egg-info/requires.txt
src/pg_rd_cf_ai_pset_2_sandhan_b.egg-info/top_level.txt