Metadata-Version: 2.1
Name: pg-rd-cf-ai-pset-2-sandhan-b
Version: 0.1.0
Summary: test
Home-page: https://github.com/pg-ds-dev-class/pset-2-dev-utils-borgohains-pg
Author: Borgohain, Sandhan
Author-email: borgohain.s@pg.com
License: Proprietary
Keywords: P&G Procter&Gamble D&A Data&Analytics
Platform: UNKNOWN
Classifier: Programming Language :: Python :: 3.7
Requires-Python: >=3.7, <=3.10
Provides-Extra: devel
License-File: LICENSE
